myfacedetect/__init__.py
myfacedetect/__version__.py
myfacedetect/cli.py
myfacedetect/config.py
myfacedetect/config.yaml
myfacedetect/config_manager.py
myfacedetect/core.py
myfacedetect/demo.py
myfacedetect/utils.py
myfacedetect/detectors/__init__.py
myfacedetect/detectors/base_detector.py
myfacedetect/detectors/detector_factory.py
myfacedetect/detectors/ensemble_detector.py
myfacedetect/detectors/haar_detector.py
myfacedetect/detectors/mediapipe_detector.py
myfacedetect/detectors/retinaface_detector.py
myfacedetect/detectors/yolov8_detector.py
myfacedetect/performance/__init__.py
myfacedetect/performance/caching.py
myfacedetect/performance/optimization.py
myfacedetect/preprocessing/__init__.py
myfacedetect/preprocessing/alignment.py
myfacedetect/preprocessing/enhancement.py
myfacedetect/recognition/__init__.py
myfacedetect/recognition/database.py
myfacedetect/recognition/face_recognition.py
myfacedetect/security/__init__.py
myfacedetect/security/liveness.py
myfacedetect/security/privacy.py
myfacedetect/testing/__init__.py
myfacedetect/utils/__init__.py
myfacedetect/utils/logging_config.py
myfacedetect/utils/onnx_utils.py
myfacedetect-0.3.0.dist-info/licenses/LICENSE
myfacedetect-0.3.0.dist-info/METADATA
myfacedetect-0.3.0.dist-info/WHEEL
myfacedetect-0.3.0.dist-info/entry_points.txt
myfacedetect-0.3.0.dist-info/top_level.txt
myfacedetect-0.3.0.dist-info/RECORD
