Metadata-Version: 2.4
Name: myfacedetect
Version: 0.3.0
Summary: High-performance face detection and recognition library with CPU-only support
Home-page: https://github.com/Santoshkrishna-code/myfacedetect
Author: Santosh Krishna
Author-email: Santosh Krishna <santoshkrishna.code@gmail.com>
Maintainer-email: Santosh Krishna <santoshkrishna.code@gmail.com>
License-Expression: MIT
Project-URL: Homepage, https://github.com/Santoshkrishna-code/myfacedetect
Project-URL: Documentation, https://github.com/Santoshkrishna-code/myfacedetect#readme
Project-URL: Repository, https://github.com/Santoshkrishna-code/myfacedetect
Project-URL: Bug Tracker, https://github.com/Santoshkrishna-code/myfacedetect/issues
Keywords: face-detection,face-recognition,opencv,mediapipe,computer-vision,cpu-only,real-time
Classifier: Development Status :: 4 - Beta
Classifier: Intended Audience :: Developers
Classifier: Intended Audience :: Science/Research
Classifier: Operating System :: OS Independent
Classifier: Programming Language :: Python :: 3
Classifier: Programming Language :: Python :: 3.8
Classifier: Programming Language :: Python :: 3.9
Classifier: Programming Language :: Python :: 3.10
Classifier: Programming Language :: Python :: 3.11
Classifier: Programming Language :: Python :: 3.12
Classifier: Topic :: Scientific/Engineering :: Image Processing
Classifier: Topic :: Software Development :: Libraries :: Python Modules
Classifier: Topic :: Multimedia :: Graphics
Requires-Python: >=3.8
License-File: LICENSE
Requires-Dist: opencv-python>=4.5.0
Requires-Dist: mediapipe>=0.9.0
Requires-Dist: numpy>=1.21.0
Requires-Dist: Pillow>=8.0.0
Requires-Dist: scikit-learn>=1.0.0
Requires-Dist: pyyaml>=5.4.0
Requires-Dist: onnxruntime>=1.10.0
Provides-Extra: dev
Requires-Dist: pytest>=6.0; extra == "dev"
Requires-Dist: pytest-cov>=2.10; extra == "dev"
Requires-Dist: black>=21.0; extra == "dev"
Requires-Dist: flake8>=3.8; extra == "dev"
Requires-Dist: mypy>=0.910; extra == "dev"
Requires-Dist: build>=0.7.0; extra == "dev"
Requires-Dist: twine>=3.4.0; extra == "dev"
Provides-Extra: examples
Requires-Dist: matplotlib>=3.3.0; extra == "examples"
Provides-Extra: gpu
Requires-Dist: onnxruntime-gpu>=1.10.0; extra == "gpu"
Provides-Extra: advanced
Requires-Dist: ultralytics>=8.0.0; extra == "advanced"
Requires-Dist: insightface>=0.7.0; extra == "advanced"
Dynamic: author
Dynamic: home-page
Dynamic: license-file
Dynamic: requires-python
